codexapi/__init__.py
codexapi/__main__.py
codexapi/agent.py
codexapi/cli.py
codexapi/foreach.py
codexapi/gh_integration.py
codexapi/pushover.py
codexapi/ralph.py
codexapi/rate_limits.py
codexapi/science.py
codexapi/task.py
codexapi/taskfile.py
codexapi-0.6.1.dist-info/LICENSE
codexapi-0.6.1.dist-info/METADATA
codexapi-0.6.1.dist-info/WHEEL
codexapi-0.6.1.dist-info/entry_points.txt
codexapi-0.6.1.dist-info/top_level.txt
codexapi-0.6.1.dist-info/RECORD
