Metadata-Version: 2.1
Name: codexapi
Version: 0.6.1
Summary: Minimal Python API for running the Codex CLI.
License: MIT
Keywords: codex,agent,cli,openai
Classifier: Programming Language :: Python :: 3
Classifier: Operating System :: OS Independent
Requires-Python: >=3.8
License-File: LICENSE
Requires-Dist: PyYAML>=6.0
Requires-Dist: gh-task>=0.1.7
Requires-Dist: tqdm>=4.64
